imanalys/__init__.py
imanalys/config.py
imanalys/file.py
imanalys/image.py
imanalys/imanalys.py
imanalys/nsfw.py
imanalys/person.py
imanalys/text.py
imanalys/data/age_deploy.prototxt
imanalys/data/age_net.caffemodel
imanalys/data/gender_deploy.prototxt
imanalys/data/gender_net.caffemodel
imanalys/data/nsfw_mobilenet2.224x224.h5
imanalys/data/opencv_face_detector.pbtxt
imanalys/data/opencv_face_detector_uint8.pb
imanalys-0.1.28.dist-info/LICENSE
imanalys-0.1.28.dist-info/WHEEL
imanalys-0.1.28.dist-info/METADATA
imanalys-0.1.28.dist-info/RECORD
