Metadata-Version: 2.1
Name: imanalys
Version: 0.1.28
Summary: Image analizer
Author-email: Alexander Bogatyrev <alexander@bogatyrev.de>
Classifier: License :: OSI Approved :: MIT License
Project-URL: Home, https://github.com/bogatyrev74/imanalys
